[
  {
    "filename" : "pino_CambiaSpacciatore.mp4",
    "kinds" : [
    ],
    "mime" : "video/mp4",
    "sources" : [
      "https://www.dropbox.com/scl/fi/lksaqec379ti3zx6ravjp/pino_CambiaSpacciatore.mp4?rlkey=82afk92sqsiapl8gr4gw7qgkf&dl=1"
    ]
  },
  {
    "filename" : "pino_CambiaSpacciatore.mp3",
    "kinds" : [
    ],
    "mime" : "audio/mpeg",
    "sources" : [
      "https://www.dropbox.com/scl/fi/4yjkzwyi8a37bupuldsvu/pino_CambiaSpacciatore.mp3?rlkey=02ztptucojimg0n1xy4mq0dif&dl=1"
    ]
  },
  {
    "filename" : "pino_CambiaSpacciatoreGif.mp4",
    "kinds" : [
    ],
    "mime" : "image/gif",
    "sources" : [
      "https://www.dropbox.com/scl/fi/n4kbq3bedbt0xpvjaigp8/pino_CambiaSpacciatoreGif.mp4?rlkey=polh64hyl80dd9169pse1xndk&dl=1"
    ]
  },
  {
    "filename" : "pino_AndateAFareInCulo.mp3",
    "kinds" : [
    ],
    "mime" : "audio/mpeg",
    "sources" : [
      "https://www.dropbox.com/scl/fi/oit2rw5yvxktgdvdxw4pz/pino_AndateAFareInCulo.mp3?rlkey=4qjpt8e5axjk0ncehwtvha6bi&dl=1"
    ]
  },
  {
    "filename" : "pino_AndateAFareInCuloGif.mp4",
    "kinds" : [
    ],
    "mime" : "image/gif",
    "sources" : [
      "https://www.dropbox.com/scl/fi/1p2t3o4dphbafbj739o8r/pino_AndateAFareInCuloGif.mp4?rlkey=1ovwi9jjb5itjwt2g75ktmaoe&dl=1"
    ]
  },
  {
    "filename" : "pino_AndateAFareInCulo.mp4",
    "kinds" : [
    ],
    "mime" : "video/mp4",
    "sources" : [
      "https://www.dropbox.com/scl/fi/fahwe0fd31qgtvtvwxvkx/pino_AndateAFareInCulo.mp4?rlkey=w0jo3gm9llpepkho2dhd3ijra&dl=1"
    ]
  },
  {
    "filename" : "pino_VafangulBastaCagateGif.mp4",
    "kinds" : [
    ],
    "mime" : "image/gif",
    "sources" : [
      "https://www.dropbox.com/scl/fi/jotz1o6u5l3ywod1011tv/pino_VafangulBastaCagateGif.mp4?rlkey=9s97u01ugho0x0w5vn8meeu49&dl=1"
    ]
  },
  {
    "filename" : "pino_VafangulBastaCagate.mp4",
    "kinds" : [
    ],
    "mime" : "video/mp4",
    "sources" : [
      "https://www.dropbox.com/scl/fi/yxq9vjgc88ajzgf6k1dxy/pino_VafangulBastaCagate.mp4?rlkey=ysw51mtf5ezfao420d00yhoml&dl=1"
    ]
  },
  {
    "filename" : "pino_VafangulBastaCagate.mp3",
    "kinds" : [
    ],
    "mime" : "audio/mpeg",
    "sources" : [
      "https://www.dropbox.com/scl/fi/8eo31wvxzrna1prlvovvp/pino_VafangulBastaCagate.mp3?rlkey=e6e66a82bojidqj8punjn7hb4&dl=1"
    ]
  },
  {
    "filename" : "pino_35anniPezzoDiMerdaSputatiFacciaDattiFuocoGif.mp4",
    "kinds" : [
    ],
    "mime" : "image/gif",
    "sources" : [
      "https://www.dropbox.com/scl/fi/y6qa2d5hrrl76d4sdb1xp/pino_35anniPezzoDiMerdaSputatiFacciaDattiFuocoGif.mp4?rlkey=yytys1jo9niz7rirx7zvrbpti&dl=1"
    ]
  },
  {
    "filename" : "pino_35anniPezzoDiMerdaSputatiFacciaDattiFuoco.mp3",
    "kinds" : [
    ],
    "mime" : "audio/mpeg",
    "sources" : [
      "https://www.dropbox.com/scl/fi/0xhmtnrjmuwjhn4e1j1tq/pino_35anniPezzoDiMerdaSputatiFacciaDattiFuoco.mp3?rlkey=uktvinl0anieoggrii7f4h0iy&dl=1"
    ]
  },
  {
    "filename" : "pino_35anniPezzoDiMerdaSputatiFacciaDattiFuoco.mp4",
    "kinds" : [
    ],
    "mime" : "video/mp4",
    "sources" : [
      "https://www.dropbox.com/scl/fi/sa59er9d7zkr28ahd8mkg/pino_35anniPezzoDiMerdaSputatiFacciaDattiFuoco.mp4?rlkey=yin0se34f7u3ofa442o4ohamo&dl=1"
    ]
  },
  {
    "filename" : "pino_Cagasentenze.mp3",
    "kinds" : [
    ],
    "mime" : "audio/mpeg",
    "sources" : [
      "https://www.dropbox.com/scl/fi/msw02dcxvxvw7eaeqmw9w/pino_Cagasentenze.mp3?rlkey=iufvi7evpb4irgydo566mi36v&dl=1"
    ]
  },
  {
    "filename" : "pino_Cagasentenze.mp4",
    "kinds" : [
    ],
    "mime" : "video/mp4",
    "sources" : [
      "https://www.dropbox.com/scl/fi/rwaglvt03n1bxwymf9bld/pino_Cagasentenze.mp4?rlkey=di0ppfvam9iucefpd0u8wut10&dl=1"
    ]
  },
  {
    "filename" : "pino_CagasentenzeGif.mp4",
    "kinds" : [
    ],
    "mime" : "image/gif",
    "sources" : [
      "https://www.dropbox.com/scl/fi/36ili0trqt3j604rwejww/pino_CagasentenzeGif.mp4?rlkey=n3htoknltucqvvod4n57bz48c&dl=1"
    ]
  },
  {
    "filename" : "pino_PapaDiJim.mp3",
    "kinds" : [
    ],
    "mime" : "audio/mpeg",
    "sources" : [
      "https://www.dropbox.com/scl/fi/d29u58hhsunnidsrsnnt1/pino_PapaDiJim.mp3?rlkey=o4nfm27nzbshpmu8mxc2vyzhm&dl=1"
    ]
  },
  {
    "filename" : "pino_PapaDiJimGif.mp4",
    "kinds" : [
    ],
    "mime" : "image/gif",
    "sources" : [
      "https://www.dropbox.com/scl/fi/dalpwikjtjw2xlonrcib3/pino_PapaDiJimGif.mp4?rlkey=92yw8nujpzvyc1pl7yqjbdrhe&dl=1"
    ]
  },
  {
    "filename" : "pino_PapaDiJim.mp4",
    "kinds" : [
    ],
    "mime" : "video/mp4",
    "sources" : [
      "https://www.dropbox.com/scl/fi/khs521sqb4xpw0y5wg419/pino_PapaDiJim.mp4?rlkey=c54k6r95hpr0vs4llow6g7wxe&dl=1"
    ]
  },
  {
    "filename" : "pino_LavavetriSorellaTroiaBaroneVaffanculo.mp4",
    "kinds" : [
    ],
    "mime" : "video/mp4",
    "sources" : [
      "https://www.dropbox.com/scl/fi/7flqncf9pm2eqgdrjgqym/pino_LavavetriSorellaTroiaBaroneVaffanculo.mp4?rlkey=u07319h57ytij2lw4t8euw6k6&dl=1"
    ]
  },
  {
    "filename" : "pino_LavavetriSorellaTroiaBaroneVaffanculoGif.mp4",
    "kinds" : [
    ],
    "mime" : "image/gif",
    "sources" : [
      "https://www.dropbox.com/scl/fi/3gsszdo79ciwtgvwvw4u8/pino_LavavetriSorellaTroiaBaroneVaffanculoGif.mp4?rlkey=pqxvwbjmz6o1hvgyi1kmsx60z&dl=1"
    ]
  },
  {
    "filename" : "pino_LavavetriSorellaTroiaBaroneVaffanculo.mp3",
    "kinds" : [
    ],
    "mime" : "audio/mpeg",
    "sources" : [
      "https://www.dropbox.com/scl/fi/rdcgzuq4eyyt5h9avwx5j/pino_LavavetriSorellaTroiaBaroneVaffanculo.mp3?rlkey=tsnju7qwd1q6u6qhtouuec3bq&dl=1"
    ]
  }
]